LICENSE
MANIFEST.in
README.md
setup.py
doctorf/__init__.py
doctorf/fields.py
doctorf/mixins.py
doctorf/parsers.py
doctorf/renderers.py
doctorf/routers.py
doctorf/serializers.py
doctorf/urls.py
doctorf/views.py
doctorf/viewsets.py
doctorf.egg-info/PKG-INFO
doctorf.egg-info/SOURCES.txt
doctorf.egg-info/dependency_links.txt
doctorf.egg-info/not-zip-safe
doctorf.egg-info/requires.txt
doctorf.egg-info/top_level.txt