Metadata-Version: 1.1
Name: doctorf
Version: 0.1.0
Summary: Extra utilities and mixins for Django REST Framework (DRF).
Home-page: https://github.com/ninemoreminutes/doctorf/
Author: Nine More Minutes, Inc.
Author-email: support@ninemoreminutes.com
License: BSD
Keywords: django rest framework
Platform: UNKNOWN
Classifier: Development Status :: 3 - Alpha
Classifier: Environment :: Web Environment
Classifier: Framework :: Django
Classifier: Intended Audience :: Developers
Classifier: License :: OSI Approved :: BSD License
Classifier: Operating System :: OS Independent
Classifier: Programming Language :: Python
Classifier: Topic :: Internet :: WWW/HTTP
Classifier: Topic :: Software Development :: Libraries
